LICENSE
MANIFEST.in
README.md
setup.py
src/hpilo_exporter/__init__.py
src/hpilo_exporter/exporter.py
src/hpilo_exporter/main.py
src/hpilo_exporter/prometheus_metrics.py
src/hpilo_exporter.egg-info/PKG-INFO
src/hpilo_exporter.egg-info/SOURCES.txt
src/hpilo_exporter.egg-info/dependency_links.txt
src/hpilo_exporter.egg-info/entry_points.txt
src/hpilo_exporter.egg-info/not-zip-safe
src/hpilo_exporter.egg-info/requires.txt
src/hpilo_exporter.egg-info/top_level.txt