Metadata-Version: 1.1
Name: hpilo-exporter
Version: 0.4.3
Summary: Prometheus exporter for HP iLO metrics
Home-page: https://github.com/infinityworks/hpilo-exporter
Author: Joe Stringer
Author-email: joe.stringer@infinityworks.com
License: MIT
Platform: UNKNOWN
Classifier: Development Status :: 4 - Beta
Classifier: Intended Audience :: System Administrators
Classifier: License :: OSI Approved :: MIT License
Classifier: Programming Language :: Python :: 2
Classifier: Programming Language :: Python :: 2.7
Classifier: Programming Language :: Python
Classifier: Topic :: Internet :: WWW/HTTP
